library_project/__init__.py
library_project/admin.py
library_project/apps.py
library_project/models.py
library_project/settings.py
library_project/urls.py
library_project/views.py
library_project/locale/en/LC_MESSAGES/django.mo
library_project/locale/en/LC_MESSAGES/django.po
library_project/migrations/0001_initial.py
library_project/migrations/__init__.py
library_project/templates/library_project/base.html
library_project/templates/library_project/index.html
django_library_project-0.1.dist-info/LICENSE.txt
django_library_project-0.1.dist-info/METADATA
django_library_project-0.1.dist-info/WHEEL
django_library_project-0.1.dist-info/top_level.txt
django_library_project-0.1.dist-info/RECORD
