Metadata-Version: 2.1
Name: django-library-project
Version: 0.1
Summary: A deployable Django app created by the cookiecutter-django-library template.
Home-page: UNKNOWN
Author: Stuart MacKay
Author-email: smackay@flagstonesoftware.com
License: License :: OSI Approved :: Apache Software License
Keywords: cookiecutter django app template
Platform: UNKNOWN
Classifier: Development Status :: 3 - Alpha
Classifier: Framework :: Django :: 2.2
Classifier: Framework :: Django :: 3.0
Classifier: Framework :: Django :: 3.1
Classifier: Intended Audience :: Developers
Classifier: License :: OSI Approved :: Apache Software License
Classifier: Natural Language :: English
Classifier: Programming Language :: Python
Classifier: Programming Language :: Python :: 3
Classifier: Programming Language :: Python :: 3.5
Classifier: Programming Language :: Python :: 3.6
Classifier: Programming Language :: Python :: 3.7
Classifier: Programming Language :: Python :: 3.8
Requires-Python: >=3.5
Requires-Dist: Django (>=2.2)
